behko_django_basic/__init__.py
behko_django_basic/apps.py
behko_django_basic/converter.py
behko_django_basic/select2.py
behko_django_basic/views.py
behko_django_basic/templates/behko_django_basic/all_in_one.html
behko_django_basic/templates/behko_django_basic/all_in_one_update.html
behko_django_basic/templates/shared/form-errors.html
behko_django_basic/templates/shared/messages.html
behko_django_basic/templatetags/__init__.py
behko_django_basic/templatetags/behko_template_utils.py
behko_django_basic/utilities/__init__.py
behko_django_basic/utilities/fields.py
behko_django_basic/utilities/helpers.py
behko_django_basic-0.0.5.dist-info/LICENSE
behko_django_basic-0.0.5.dist-info/METADATA
behko_django_basic-0.0.5.dist-info/WHEEL
behko_django_basic-0.0.5.dist-info/top_level.txt
behko_django_basic-0.0.5.dist-info/RECORD
