Metadata-Version: 2.1
Name: behko-django-basic
Version: 0.0.5
Summary: Makes it easier
Home-page: https://github.com/powerfuldeveloper/cool_utils
Author: powerfuldeveloper
Author-email: apowerfuldeveloper@gmail.com
License: UNKNOWN
Platform: UNKNOWN
Classifier: Programming Language :: Python :: 3
Classifier: License :: OSI Approved :: MIT License
Classifier: Operating System :: OS Independent
Requires-Python: >=3.6
